chainfury/__init__.py
chainfury/__main__.py
chainfury/agent.py
chainfury/base.py
chainfury/cli.py
chainfury/client.py
chainfury/components/README.md
chainfury/components/__init__.py
chainfury/components/ai_actions/__init__.py
chainfury/components/const.py
chainfury/components/functional/__init__.py
chainfury/components/openai/__init__.py
chainfury/components/qdrant/__init__.py
chainfury/components/serper/__init__.py
chainfury/components/stability/__init__.py
chainfury/components/tune/__init__.py
chainfury/types.py
chainfury/utils.py
chainfury/version.py
chainfury-1.6.4.dist-info/LICENSE
chainfury-1.6.4.dist-info/METADATA
chainfury-1.6.4.dist-info/WHEEL
chainfury-1.6.4.dist-info/entry_points.txt
chainfury-1.6.4.dist-info/RECORD
