Metadata-Version: 2.1
Name: chainfury
Version: 1.6.4
Summary: ChainFury is a powerful tool that simplifies the creation and management of chains of prompts, making it easier to build complex chat applications using LLMs.
Home-page: https://github.com/NimbleBoxAI/ChainFury
License: Apache 2.0
Author: NimbleBox Engineering
Author-email: engineering@nimblebox.ai
Requires-Python: >=3.9,<3.12
Classifier: License :: Other/Proprietary License
Classifier: Programming Language :: Python :: 3
Classifier: Programming Language :: Python :: 3.9
Classifier: Programming Language :: Python :: 3.10
Classifier: Programming Language :: Python :: 3.11
Provides-Extra: all
Provides-Extra: qdrant
Provides-Extra: stability
Requires-Dist: Jinja2 (==3.1.2)
Requires-Dist: boto3 (==1.29.6) ; extra == "all"
Requires-Dist: cryptography (>=41.0.6)
Requires-Dist: fire (==0.5.0)
Requires-Dist: jinja2schema (==0.1.4)
Requires-Dist: pydantic (>=1.10.7,<2.0.0)
Requires-Dist: python-dotenv (==1.0.0)
Requires-Dist: qdrant-client (==1.5.4) ; extra == "all" or extra == "qdrant"
Requires-Dist: requests (>=2.31.0,<3.0.0)
Requires-Dist: stability-sdk (==0.8.3) ; extra == "all" or extra == "stability"
Requires-Dist: urllib3 (>=1.26.18)
Project-URL: Repository, https://github.com/NimbleBoxAI/ChainFury
